libraw.py
setup.py
libraw.py.egg-info/PKG-INFO
libraw.py.egg-info/SOURCES.txt
libraw.py.egg-info/dependency_links.txt
libraw.py.egg-info/top_level.txt