Metadata-Version: 1.1
Name: libraw.py
Version: 1.0
Summary: python bindings using ctypes for libraw
Home-page: https://github.com/paroj/libraw.py
Author: Pavel Rojtberg
Author-email: UNKNOWN
License: LGPLv2
Platform: UNKNOWN
Classifier: Programming Language :: Python :: 2.7
Classifier: Programming Language :: Python :: 3
